_jpype.cp37-win_amd64.pyd
jpype/JClassUtil.py
jpype/__init__.py
jpype/_core.py
jpype/_cygwin.py
jpype/_darwin.py
jpype/_gui.py
jpype/_jarray.py
jpype/_jclass.py
jpype/_jcollection.py
jpype/_jexception.py
jpype/_jobject.py
jpype/_jpackage.py
jpype/_jproxy.py
jpype/_jvmfinder.py
jpype/_jwrapper.py
jpype/_linux.py
jpype/_properties.py
jpype/_pykeywords.py
jpype/_refdaemon.py
jpype/_windows.py
jpype/nio.py
jpype/reflect.py
jpype/awt/__init__.py
jpype/awt/event/WindowAdapter.py
jpype/awt/event/__init__.py
jpypex/__init__.py
jpypex/swing/AbstractAction.py
jpypex/swing/__init__.py
jpypex/swing/pyutils.py
JPype1_py3-0.5.5.4.dist-info/LICENSE.txt
JPype1_py3-0.5.5.4.dist-info/METADATA
JPype1_py3-0.5.5.4.dist-info/WHEEL
JPype1_py3-0.5.5.4.dist-info/top_level.txt
JPype1_py3-0.5.5.4.dist-info/RECORD
