Metadata-Version: 1.2
Name: JPype1-py3
Version: 0.5.5.4
Summary: Python-Java bridge. Fork of the jPype project by Steve Menard (http://jpype.sourceforge.net/), with the modifications applied by Luis Nell (https://github.com/originell/jpype)
Home-page: http://github.com/tcalmant/jpype-py3/
Author: Steve Menard
Author-email: devilwolf@users.sourceforge.net
Maintainer: Thomas Calmant
Maintainer-email: thomas.calmant@gmail.com
License: License :: OSI Approved :: Apache Software License
Platform: Operating System :: MacOS :: MacOS X
Platform: Operating System :: Microsoft :: Windows :: Windows 7
Platform: Operating System :: Microsoft :: Windows :: Windows Vista
Platform: Operating System :: POSIX :: Linux
Classifier: Intended Audience :: Developers
Classifier: License :: OSI Approved :: Apache Software License
Classifier: Programming Language :: Java
Classifier: Programming Language :: Python :: 3
Classifier: Development Status :: 7 - Inactive
